README.rst
setup.py
twqq/__init__.py
twqq/_hash.py
twqq/client.py
twqq/const.py
twqq/hub.py
twqq/objects.py
twqq/requests.py
twqq.egg-info/PKG-INFO
twqq.egg-info/SOURCES.txt
twqq.egg-info/dependency_links.txt
twqq.egg-info/requires.txt
twqq.egg-info/top_level.txt