Metadata-Version: 1.1
Name: twqq
Version: 0.2.1
Summary: An asynchronous webqq client library based on tornado
Home-page: http://www.linuxzen.com
Author: cold
Author-email: wh_linux@126.com
License: Apache 2.0
Platform: any
Classifier: Development Status :: 3 - Alpha
Classifier: Environment :: Console
Classifier: Intended Audience :: Developers
Classifier: License :: OSI Approved :: Apache Software License
Classifier: Topic :: Internet :: WWW/HTTP
Classifier: Programming Language :: Python :: 2.7
